fb8-1.2.8.dist-info/licenses/LICENSE
sphere/__init__.py
sphere/distribution/__init__.py
sphere/distribution/distribution.py
sphere/distribution/saddle.py
sphere/example/__init__.py
sphere/example/example.py
fb8-1.2.8.dist-info/METADATA
fb8-1.2.8.dist-info/WHEEL
fb8-1.2.8.dist-info/top_level.txt
fb8-1.2.8.dist-info/RECORD
