Metadata-Version: 2.4
Name: fb8
Version: 1.2.8
Summary: Implementation of FB8, a generalization of the Kent (1982) and Bingham-Mardia (1978) distributions on a sphere
Author-email: Tianlu Yuan <tyuan@icecube.wisc.edu>, Daniël Fraenkel <e.d.fraenkel@gmail.com>, Austin Schneider <aschn@mit.edu>
Maintainer-email: Tianlu Yuan <tyuan@icecube.wisc.edu>
License: MIT License
Project-URL: Repository, https://github.com/tianluyuan/sphere.git
Classifier: Intended Audience :: Science/Research
Classifier: License :: OSI Approved :: MIT License
Classifier: Natural Language :: English
Classifier: Programming Language :: Python :: 3
Classifier: Topic :: Scientific/Engineering
Requires-Python: >=3.9
License-File: LICENSE
Requires-Dist: numpy>=1.17
Requires-Dist: scipy>=1.4
Provides-Extra: plotting
Requires-Dist: matplotlib>=3.2; extra == "plotting"
Requires-Dist: healpy; extra == "plotting"
Dynamic: license-file
